elevator_game/Building.py
elevator_game/CannotLoadError.py
elevator_game/Difficulty.py
elevator_game/Elevator.py
elevator_game/Game.py
elevator_game/NoDifficultyError.py
elevator_game/NoElevatorError.py
elevator_game/NoFloorError.py
elevator_game/Person.py
elevator_game/__init__.py
elevator_game/__main__.py
elevator_game/curses.py
elevator_game-1.0.3.dist-info/LICENSE
elevator_game-1.0.3.dist-info/METADATA
elevator_game-1.0.3.dist-info/WHEEL
elevator_game-1.0.3.dist-info/top_level.txt
elevator_game-1.0.3.dist-info/RECORD
