Metadata-Version: 2.1
Name: elevator-game
Version: 1.0.3
Summary: A TUI game where you control elevators.
Home-page: https://github.com/smwa/elevator_game
Author: Michael Smith
Author-email: michael.smith.ok@gmail.com
Classifier: Programming Language :: Python :: 3
Classifier: License :: OSI Approved :: MIT License
Classifier: Operating System :: OS Independent
Requires-Python: >=3.6
License-File: LICENSE
